.gitignore
LICENSE
README.md
pyproject.toml
.github/workflows/release.yaml
.github/workflows/test.yaml
mock/Dockerfile
mock/README.md
mock/pyproject.toml
mock/mock_da4_server/__main__.py
mock/mock_da4_server/check.py
mock/mock_da4_server/job.py
mock/mock_da4_server/main.py
mock/mock_da4_server/models.py
mock/mock_da4_server/random_qubo_response.py
ommx_da4_adapter/__init__.py
ommx_da4_adapter/_version.py
ommx_da4_adapter/adapter.py
ommx_da4_adapter/client.py
ommx_da4_adapter/exception.py
ommx_da4_adapter/models.py
ommx_da4_adapter.egg-info/PKG-INFO
ommx_da4_adapter.egg-info/SOURCES.txt
ommx_da4_adapter.egg-info/dependency_links.txt
ommx_da4_adapter.egg-info/requires.txt
ommx_da4_adapter.egg-info/top_level.txt
tests/test_adapter.py
tests/test_client.py