Metadata-Version: 2.4
Name: ommx_da4_adapter
Version: 0.1.0rc1
Summary: An adapter for the Digital Annealer V4 from/to OMMX.
Author-email: "Jij Inc." <info@j-ij.com>
Project-URL: Repository, https://github.com/Jij-Inc/ommx-da4-adapter
Project-URL: Issues, https://github.com/Jij-Inc/ommx-da4-adapter/issues
Classifier: Programming Language :: Python :: 3 :: Only
Classifier: Programming Language :: Python :: 3.9
Classifier: Programming Language :: Python :: 3.10
Classifier: Programming Language :: Python :: 3.11
Classifier: Programming Language :: Python :: 3.12
Classifier: License :: OSI Approved :: Apache Software License
Requires-Python: >=3.9
License-File: LICENSE
Requires-Dist: ommx<2.1.0,>=2.0.0rc4
Requires-Dist: requests<3.0.0,>=2.25.0
Requires-Dist: pydantic<3.0.0,>=2.10.0
Provides-Extra: dev
Requires-Dist: pyright; extra == "dev"
Requires-Dist: pytest; extra == "dev"
Requires-Dist: ruff; extra == "dev"
Dynamic: license-file
